[
  {
    "id": 0,
    "name": "Kitchen",
    "nodeaddress": 252,
    "unitaddress": 100,
    "destinations": [
      {
        "id": 0,
        "destinationnr": 0,
        "name": "Kitchen",
        "nodeaddress": 252,
        "unitaddress": 100,
        "maxvolume": 100,
        "type": 1,
        "sources": [
          {
            "id": 0,
            "sourcenr": 0,
            "name": "Joe",
            "nodeaddress": 252,
            "unitaddress": 100
          },
          {
            "id": 1,
            "sourcenr": 1,
            "name": "Joe Easy",
            "nodeaddress": 252,
            "unitaddress": 100
          },
          {
            "id": 2,
            "sourcenr": 2,
            "name": "MNM",
            "nodeaddress": 252,
            "unitaddress": 100
          },
          {
            "id": 3,
            "sourcenr": 3,
            "name": "Radio 2",
            "nodeaddress": 252,
            "unitaddress": 100
          },
          {
            "id": 4,
            "sourcenr": 4,
            "name": "StuBru",
            "nodeaddress": 252,
            "unitaddress": 100
          },
          {
            "id": 5,
            "sourcenr": 7,
            "name": "Radio 1",
            "nodeaddress": 252,
            "unitaddress": 100
          },
          {
            "id": 6,
            "sourcenr": 6,
            "name": "VRT nieuws",
            "nodeaddress": 252,
            "unitaddress": 100
          },
          {
            "id": 7,
            "sourcenr": 5,
            "name": "Living inp b&o",
            "nodeaddress": 252,
            "unitaddress": 100
          }
        ]
      }
    ]
  },
  {
    "id": 1,
    "name": "Tim Bedroom",
    "nodeaddress": 252,
    "unitaddress": 101,
    "destinations": [
      {
        "id": 0,
        "destinationnr": 1,
        "name": "Tim Bedroom",
        "nodeaddress": 252,
        "unitaddress": 101,
        "maxvolume": 100,
        "type": 1,
        "sources": [
          {
            "id": 0,
            "sourcenr": 1,
            "name": "Joe Easy",
            "nodeaddress": 252,
            "unitaddress": 101
          },
          {
            "id": 1,
            "sourcenr": 0,
            "name": "Joe",
            "nodeaddress": 252,
            "unitaddress": 101
          },
          {
            "id": 2,
            "sourcenr": 2,
            "name": "MNM",
            "nodeaddress": 252,
            "unitaddress": 101
          },
          {
            "id": 3,
            "sourcenr": 3,
            "name": "Radio 2",
            "nodeaddress": 252,
            "unitaddress": 101
          },
          {
            "id": 4,
            "sourcenr": 4,
            "name": "StuBru",
            "nodeaddress": 252,
            "unitaddress": 101
          },
          {
            "id": 5,
            "sourcenr": 7,
            "name": "Radio 1",
            "nodeaddress": 252,
            "unitaddress": 101
          },
          {
            "id": 6,
            "sourcenr": 6,
            "name": "VRT nieuws",
            "nodeaddress": 252,
            "unitaddress": 101
          },
          {
            "id": 7,
            "sourcenr": 5,
            "name": "Living inp b&o",
            "nodeaddress": 252,
            "unitaddress": 101
          }
        ]
      }
    ]
  },
  {
    "id": 2,
    "name": "Master Bedroom",
    "nodeaddress": 252,
    "unitaddress": 102,
    "destinations": [
      {
        "id": 0,
        "destinationnr": 3,
        "name": "Master Bedroom",
        "nodeaddress": 252,
        "unitaddress": 102,
        "maxvolume": 100,
        "type": 1,
        "sources": [
          {
            "id": 0,
            "sourcenr": 0,
            "name": "Joe",
            "nodeaddress": 252,
            "unitaddress": 102
          },
          {
            "id": 1,
            "sourcenr": 1,
            "name": "Joe Easy",
            "nodeaddress": 252,
            "unitaddress": 102
          },
          {
            "id": 2,
            "sourcenr": 2,
            "name": "MNM",
            "nodeaddress": 252,
            "unitaddress": 102
          },
          {
            "id": 3,
            "sourcenr": 3,
            "name": "Radio 2",
            "nodeaddress": 252,
            "unitaddress": 102
          },
          {
            "id": 4,
            "sourcenr": 4,
            "name": "StuBru",
            "nodeaddress": 252,
            "unitaddress": 102
          },
          {
            "id": 5,
            "sourcenr": 7,
            "name": "Radio 1",
            "nodeaddress": 252,
            "unitaddress": 102
          },
          {
            "id": 6,
            "sourcenr": 6,
            "name": "VRT nieuws",
            "nodeaddress": 252,
            "unitaddress": 102
          },
          {
            "id": 7,
            "sourcenr": 5,
            "name": "Living inp b&o",
            "nodeaddress": 252,
            "unitaddress": 102
          }
        ]
      }
    ]
  },
  {
    "id": 3,
    "name": "Living",
    "nodeaddress": 252,
    "unitaddress": 103,
    "destinations": [
      {
        "id": 0,
        "destinationnr": 2,
        "name": "Living",
        "nodeaddress": 252,
        "unitaddress": 103,
        "maxvolume": 100,
        "type": 1,
        "sources": [
          {
            "id": 0,
            "sourcenr": 0,
            "name": "Joe",
            "nodeaddress": 252,
            "unitaddress": 103
          },
          {
            "id": 1,
            "sourcenr": 1,
            "name": "Joe Easy",
            "nodeaddress": 252,
            "unitaddress": 103
          },
          {
            "id": 2,
            "sourcenr": 2,
            "name": "MNM",
            "nodeaddress": 252,
            "unitaddress": 103
          },
          {
            "id": 3,
            "sourcenr": 3,
            "name": "Radio 2",
            "nodeaddress": 252,
            "unitaddress": 103
          },
          {
            "id": 4,
            "sourcenr": 4,
            "name": "StuBru",
            "nodeaddress": 252,
            "unitaddress": 103
          },
          {
            "id": 5,
            "sourcenr": 7,
            "name": "Radio 1",
            "nodeaddress": 252,
            "unitaddress": 103
          },
          {
            "id": 6,
            "sourcenr": 6,
            "name": "VRT nieuws",
            "nodeaddress": 252,
            "unitaddress": 103
          },
          {
            "id": 7,
            "sourcenr": 5,
            "name": "Living inp b&o",
            "nodeaddress": 252,
            "unitaddress": 103
          }
        ]
      }
    ]
  },
  {
    "id": 4,
    "name": "Video matrix",
    "nodeaddress": 252,
    "unitaddress": 104,
    "destinations": [
      {
        "id": 1,
        "destinationnr": 4,
        "name": "Living TV",
        "nodeaddress": 252,
        "unitaddress": 104,
        "maxvolume": 100,
        "type": 2,
        "sources": [
          {
            "id": 0,
            "sourcenr": 9,
            "name": "DVD",
            "nodeaddress": 252,
            "unitaddress": 104
          },
          {
            "id": 1,
            "sourcenr": 10,
            "name": "Apple TV",
            "nodeaddress": 252,
            "unitaddress": 104
          },
          {
            "id": 2,
            "sourcenr": 8,
            "name": "Digibox",
            "nodeaddress": 252,
            "unitaddress": 104
          }
        ]
      }
    ]
  },
  {
    "id": 5,
    "name": "Both",
    "nodeaddress": 252,
    "unitaddress": 105,
    "destinations": [
      {
        "id": 0,
        "destinationnr": 0,
        "name": "Kitchen",
        "nodeaddress": 252,
        "unitaddress": 105,
        "maxvolume": 100,
        "type": 1,
        "sources": [
          {
            "id": 0,
            "sourcenr": 0,
            "name": "Joe",
            "nodeaddress": 252,
            "unitaddress": 105
          },
          {
            "id": 1,
            "sourcenr": 1,
            "name": "Joe Easy",
            "nodeaddress": 252,
            "unitaddress": 105
          },
          {
            "id": 2,
            "sourcenr": 2,
            "name": "MNM",
            "nodeaddress": 252,
            "unitaddress": 105
          },
          {
            "id": 3,
            "sourcenr": 3,
            "name": "Radio 2",
            "nodeaddress": 252,
            "unitaddress": 105
          },
          {
            "id": 4,
            "sourcenr": 4,
            "name": "StuBru",
            "nodeaddress": 252,
            "unitaddress": 105
          },
          {
            "id": 5,
            "sourcenr": 7,
            "name": "Radio 1",
            "nodeaddress": 252,
            "unitaddress": 105
          },
          {
            "id": 6,
            "sourcenr": 7,
            "name": "Radio 1",
            "nodeaddress": 252,
            "unitaddress": 105
          },
          {
            "id": 7,
            "sourcenr": 5,
            "name": "Living inp b&o",
            "nodeaddress": 252,
            "unitaddress": 105
          }
        ]
      },
      {
        "id": 1,
        "destinationnr": 1,
        "name": "Tim Bedroom",
        "nodeaddress": 252,
        "unitaddress": 105,
        "maxvolume": 100,
        "type": 1,
        "sources": [
          {
            "id": 0,
            "sourcenr": 0,
            "name": "Joe",
            "nodeaddress": 252,
            "unitaddress": 105
          },
          {
            "id": 1,
            "sourcenr": 1,
            "name": "Joe Easy",
            "nodeaddress": 252,
            "unitaddress": 105
          },
          {
            "id": 2,
            "sourcenr": 2,
            "name": "MNM",
            "nodeaddress": 252,
            "unitaddress": 105
          },
          {
            "id": 3,
            "sourcenr": 3,
            "name": "Radio 2",
            "nodeaddress": 252,
            "unitaddress": 105
          },
          {
            "id": 4,
            "sourcenr": 4,
            "name": "StuBru",
            "nodeaddress": 252,
            "unitaddress": 105
          },
          {
            "id": 5,
            "sourcenr": 7,
            "name": "Radio 1",
            "nodeaddress": 252,
            "unitaddress": 105
          },
          {
            "id": 6,
            "sourcenr": 7,
            "name": "Radio 1",
            "nodeaddress": 252,
            "unitaddress": 105
          },
          {
            "id": 7,
            "sourcenr": 5,
            "name": "Living inp b&o",
            "nodeaddress": 252,
            "unitaddress": 105
          }
        ]
      },
      {
        "id": 2,
        "destinationnr": 2,
        "name": "Living",
        "nodeaddress": 252,
        "unitaddress": 105,
        "maxvolume": 100,
        "type": 1,
        "sources": [
          {
            "id": 0,
            "sourcenr": 0,
            "name": "Joe",
            "nodeaddress": 252,
            "unitaddress": 105
          },
          {
            "id": 1,
            "sourcenr": 1,
            "name": "Joe Easy",
            "nodeaddress": 252,
            "unitaddress": 105
          },
          {
            "id": 2,
            "sourcenr": 2,
            "name": "MNM",
            "nodeaddress": 252,
            "unitaddress": 105
          },
          {
            "id": 3,
            "sourcenr": 3,
            "name": "Radio 2",
            "nodeaddress": 252,
            "unitaddress": 105
          },
          {
            "id": 4,
            "sourcenr": 4,
            "name": "StuBru",
            "nodeaddress": 252,
            "unitaddress": 105
          },
          {
            "id": 5,
            "sourcenr": 7,
            "name": "Radio 1",
            "nodeaddress": 252,
            "unitaddress": 105
          },
          {
            "id": 6,
            "sourcenr": 7,
            "name": "Radio 1",
            "nodeaddress": 252,
            "unitaddress": 105
          },
          {
            "id": 7,
            "sourcenr": 5,
            "name": "Living inp b&o",
            "nodeaddress": 252,
            "unitaddress": 105
          }
        ]
      },
      {
        "id": 3,
        "destinationnr": 3,
        "name": "Master Bedroom",
        "nodeaddress": 252,
        "unitaddress": 105,
        "maxvolume": 100,
        "type": 1,
        "sources": [
          {
            "id": 0,
            "sourcenr": 0,
            "name": "Joe",
            "nodeaddress": 252,
            "unitaddress": 105
          },
          {
            "id": 1,
            "sourcenr": 1,
            "name": "Joe Easy",
            "nodeaddress": 252,
            "unitaddress": 105
          },
          {
            "id": 2,
            "sourcenr": 2,
            "name": "MNM",
            "nodeaddress": 252,
            "unitaddress": 105
          },
          {
            "id": 3,
            "sourcenr": 3,
            "name": "Radio 2",
            "nodeaddress": 252,
            "unitaddress": 105
          },
          {
            "id": 4,
            "sourcenr": 4,
            "name": "StuBru",
            "nodeaddress": 252,
            "unitaddress": 105
          },
          {
            "id": 5,
            "sourcenr": 7,
            "name": "Radio 1",
            "nodeaddress": 252,
            "unitaddress": 105
          },
          {
            "id": 6,
            "sourcenr": 7,
            "name": "Radio 1",
            "nodeaddress": 252,
            "unitaddress": 105
          },
          {
            "id": 7,
            "sourcenr": 5,
            "name": "Living inp b&o",
            "nodeaddress": 252,
            "unitaddress": 105
          }
        ]
      }
    ]
  },
  {
    "id": 64,
    "name": "Virtual Test",
    "nodeaddress": 255,
    "unitaddress": 0,
    "destinations": [
      {
        "id": 0,
        "destinationnr": 2,
        "name": "Living",
        "nodeaddress": 252,
        "unitaddress": 103,
        "maxvolume": 100,
        "type": 1,
        "sources": [
          {
            "id": 0,
            "sourcenr": 0,
            "name": "Joe",
            "nodeaddress": 252,
            "unitaddress": 103
          },
          {
            "id": 1,
            "sourcenr": 1,
            "name": "Joe Easy",
            "nodeaddress": 252,
            "unitaddress": 103
          },
          {
            "id": 2,
            "sourcenr": 2,
            "name": "MNM",
            "nodeaddress": 252,
            "unitaddress": 103
          },
          {
            "id": 3,
            "sourcenr": 3,
            "name": "Radio 2",
            "nodeaddress": 252,
            "unitaddress": 103
          },
          {
            "id": 4,
            "sourcenr": 4,
            "name": "StuBru",
            "nodeaddress": 252,
            "unitaddress": 103
          },
          {
            "id": 5,
            "sourcenr": 7,
            "name": "Radio 1",
            "nodeaddress": 252,
            "unitaddress": 103
          },
          {
            "id": 6,
            "sourcenr": 6,
            "name": "VRT nieuws",
            "nodeaddress": 252,
            "unitaddress": 103
          },
          {
            "id": 7,
            "sourcenr": 5,
            "name": "Living inp b&o",
            "nodeaddress": 252,
            "unitaddress": 103
          }
        ]
      },
      {
        "id": 1,
        "destinationnr": 4,
        "name": "Living TV",
        "nodeaddress": 252,
        "unitaddress": 104,
        "maxvolume": 100,
        "type": 2,
        "sources": [
          {
            "id": 0,
            "sourcenr": 9,
            "name": "DVD",
            "nodeaddress": 252,
            "unitaddress": 104
          },
          {
            "id": 1,
            "sourcenr": 10,
            "name": "Apple TV",
            "nodeaddress": 252,
            "unitaddress": 104
          },
          {
            "id": 2,
            "sourcenr": 8,
            "name": "Digibox",
            "nodeaddress": 252,
            "unitaddress": 104
          }
        ]
      }
    ]
  }
]